skill_about/LICENSE.md
skill_about/README.md
skill_about/__init__.py
skill_about/skill.json
skill_about/version.py
skill_about/locale/en-us/dialog/license_long.dialog
skill_about/locale/en-us/dialog/license_short.dialog
skill_about/locale/en-us/dialog/skills_list.dialog
skill_about/locale/en-us/vocab/license.voc
skill_about/locale/en-us/vocab/long.voc
skill_about/locale/en-us/vocab/skills.voc
skill_about/locale/en-us/vocab/tell.voc
skill_about/locale/uk-ua/dialog/license_long.dialog
skill_about/locale/uk-ua/dialog/license_short.dialog
skill_about/locale/uk-ua/dialog/skills_list.dialog
skill_about/locale/uk-ua/vocab/license.voc
skill_about/locale/uk-ua/vocab/long.voc
skill_about/locale/uk-ua/vocab/skills.voc
skill_about/locale/uk-ua/vocab/tell.voc
skill_about/neon_skill_about.egg-info/PKG-INFO
skill_about/neon_skill_about.egg-info/SOURCES.txt
skill_about/neon_skill_about.egg-info/dependency_links.txt
skill_about/neon_skill_about.egg-info/entry_points.txt
skill_about/neon_skill_about.egg-info/requires.txt
skill_about/neon_skill_about.egg-info/top_level.txt
skill_about/test/test_skill.py
neon_skill_about-1.0.3.dist-info/LICENSE.md
neon_skill_about-1.0.3.dist-info/METADATA
neon_skill_about-1.0.3.dist-info/WHEEL
neon_skill_about-1.0.3.dist-info/entry_points.txt
neon_skill_about-1.0.3.dist-info/top_level.txt
neon_skill_about-1.0.3.dist-info/RECORD
